simple_package/_init_.py
simple_package/dummy.py
my_first_dummy_package-0.1.dist-info/METADATA
my_first_dummy_package-0.1.dist-info/WHEEL
my_first_dummy_package-0.1.dist-info/top_level.txt
my_first_dummy_package-0.1.dist-info/RECORD
