Metadata-Version: 2.1
Name: my-first-dummy-package
Version: 0.1
Summary: My own dummy package for lab2
Home-page: UNKNOWN
License: UNKNOWN
Platform: UNKNOWN
Requires-Dist: pandas (<1.0)
